[
    {
        "reference": "RESUPPLY",
        "name": "Ravitaillez"
    },
    {
        "reference": "SEASONED",
        "name": "Aguerri"
    },
    {
        "reference": "BOOSTED",
        "name": "Boosté"
    },
    {
        "reference": "BRASSBUG",
        "name": "2/2/2 Scarabot"
    },
    {
        "reference": "SABOTAGE",
        "name": "Sabotez"
    },
    {
        "reference": "BOODA",
        "name": "2/2/2 Booda"
    },
    {
        "reference": "ORDIS_RECRUIT",
        "name": "1/1/1 Recrue Ordis"
    },
    {
        "reference": "GIGANTIC",
        "name": "Gigantesque"
    },
    {
        "reference": "TOUGH_1",
        "name": "Coriace 1"
    },
    {
        "reference": "TOUGH_2",
        "name": "Coriace 2"
    },
    {
        "reference": "TOUGH_X",
        "name": "Coriace X"
    },
    {
        "reference": "DEFENDER",
        "name": "Défenseur"
    },
    {
        "reference": "ETERNAL",
        "name": "Éternel"
    },
    {
        "reference": "AFTER_YOU",
        "name": "Après vous"
    },
    {
        "reference": "MAW",
        "name": "0/0/0 Maw"
    },
    {
        "reference": "ANCHORED",
        "name": "Ancré"
    },
    {
        "reference": "FLEETING",
        "name": "Fugace"
    },
    {
        "reference": "ASLEEP",
        "name": "Endormi"
    }
]